bitdict/__init__.py
bitdict/bitdict.py
bitdict/markdown.py
bitdict-1.0.0.dist-info/LICENSE
bitdict-1.0.0.dist-info/METADATA
bitdict-1.0.0.dist-info/WHEEL
bitdict-1.0.0.dist-info/top_level.txt
bitdict-1.0.0.dist-info/RECORD
