Metadata-Version: 2.2
Name: bitdict
Version: 1.0.0
Summary: BitDict is a Python library for creating custom bit-packed data structures with dynamically defined substructures.
Author-email: Shaped Sundew <shapedsundew9@gmail.com>
Project-URL: Homepage, https://github.com/Shapedsundew9/bitdict
Project-URL: Documentation, https://github.com/Shapedsundew9/bitdict/blob/main/README.md
Project-URL: Repository, https://github.com/Shapedsundew9/bitdict
Project-URL: Issues, https://github.com/Shapedsundew9/bitdict/issues
Project-URL: Changelog, https://github.com/Shapedsundew9/bitdict/blob/main/CHANGELOG.md
Keywords: bitstruct,bitfield,bitpacked
Classifier: Development Status :: 5 - Production/Stable
Classifier: Intended Audience :: Developers
Classifier: Topic :: Software Development
Classifier: License :: OSI Approved :: MIT License
Classifier: Natural Language :: English
Classifier: Programming Language :: Python :: 3.10
Classifier: Programming Language :: Python :: 3.11
Classifier: Programming Language :: Python :: 3.12
Classifier: Programming Language :: Python :: 3.13
Requires-Python: >=3.10
License-File: LICENSE
